{
    "Changes": [
        {
            "LogName": "Arbitrary - 25238/code/Maps/Additions - DeveloperNotes",
            "Action": "EditData",
            "Target": "Characters/Dialogue/MPP_EK_DeveloperNotes",
            "Entries": {
                "DeveloperNotes_Maps_Additions_Arbitrary.001": "+--------------------------------------------+",
                "DeveloperNotes_Maps_Additions_Arbitrary.002": "|              Maps/Arbitrary                |",
                "DeveloperNotes_Maps_Additions_Arbitrary.003": "+--------------------------------------------+"
            }
        },
        {
            "LogName": "Arbitrary - Map Addition - AdventureGuild",
            "Action": "Load",
            "Target": "Data/Events/AdventureGuild",
            "FromFile": "code/blank.json",
            "When": null
        },
        {
            "LogName": "Arbitrary - Map Addition - Desert",
            "Action": "Load",
            "Target": "Data/Events/Desert",
            "FromFile": "code/blank.json",
            "When": null
        },
        {
            "LogName": "Arbitrary - Map Addition - MPP_EK_CharacterLobby",
            "Action": "Load",
            "Target": "Maps/MPP_EK_CharacterLobby",
            "FromFile": "assets/Maps/MPP_EK_CharacterLobby.tmx",
            "When": null
        },

        
        {
            "LogName": "Dhampir - 25238/code/Maps/Additions - DeveloperNotes",
            "Action": "EditData",
            "Target": "Characters/Dialogue/MPP_EK_DeveloperNotes",
            "Entries": {
                "DeveloperNotes_Maps_Additions_Dhampir.001": "+--------------------------------------------+",
                "DeveloperNotes_Maps_Additions_Dhampir.002": "|                Maps/Dhampir                |",
                "DeveloperNotes_Maps_Additions_Dhampir.003": "+--------------------------------------------+"
            }
        },
        {
            "LogName": "Dhampir - Map Addition - MPP_EK_DhampirRoom",
            "Action": "Load",
            "Target": "Maps/MPP_EK_DhampirRoom",
            "FromFile": "assets/Maps/MPP_EK_DhampirRoom.tmx",
            "When": null
        },
        {
            "LogName": "Dhampir - Map Addition - MPP_EK_DhampirSpouseArea",
            "Action": "Load",
            "Target": "Maps/MPP_EK_DhampirSpouseArea",
            "FromFile": "assets/Maps/MPP_EK_DhampirSpouseArea.tmx",
            "When": null
        },
        {
            "LogName": "Dhampir - Map Addition - MPP_EK_DhampirSpouseRoom",
            "Action": "Load",
            "Target": "Maps/MPP_EK_DhampirSpouseRoom",
            "FromFile": "assets/Maps/MPP_EK_DhampirSpouseRoom.tmx",
            "When": null
        },
        {
            "LogName": "Dhampir - Map Addition - MPP_EK_Hospital",
            "Action": "Load",
            "Target": "Maps/MPP_EK_Hospital",
            "FromFile": "assets/Maps/MPP_EK_Hospital.tmx",
            "When": null
        },
        {
            "LogName": "Dhampir - Map Addition - MPP_EK_ScienceHouse",
            "Action": "Load",
            "Target": "Maps/MPP_EK_ScienceHouse",
            "FromFile": "assets/Maps/MPP_EK_ScienceHouse.tmx",
            "When": null
        },

        
        {
            "LogName": "Djinn - 25238/code/Maps/Additions - DeveloperNotes",
            "Action": "EditData",
            "Target": "Characters/Dialogue/MPP_EK_DeveloperNotes",
            "Entries": {
                "DeveloperNotes_Maps_Additions_Djinn.001": "+--------------------------------------------+",
                "DeveloperNotes_Maps_Additions_Djinn.002": "|                 Maps/Djinn                 |",
                "DeveloperNotes_Maps_Additions_Djinn.003": "+--------------------------------------------+"
            }
        },
        {
            "LogName": "Djinn - Map Addition - MPP_EK_CourtHouse",
            "Action": "Load",
            "Target": "Maps/MPP_EK_CourtHouse",
            "FromFile": "assets/Maps/MPP_EK_CourtHouse.tmx",
            "When": null
        },
        {
            "LogName": "Djinn - Map Addition - MPP_EK_DesertTruck",
            "Action": "Load",
            "Target": "Maps/MPP_EK_DesertTruck",
            "FromFile": "assets/Maps/MPP_EK_DesertTruck.tmx",
            "When": null
        },
        {
            "LogName": "Djinn - Map Addition - MPP_EK_DjinnSpouseArea",
            "Action": "Load",
            "Target": "Maps/MPP_EK_DjinnSpouseArea",
            "FromFile": "assets/Maps/MPP_EK_DjinnSpouseArea.tmx",
            "When": null
        },
        {
            "LogName": "Djinn - Map Addition - MPP_EK_DjinnSpouseRoom",
            "Action": "Load",
            "Target": "Maps/MPP_EK_DjinnSpouseRoom",
            "FromFile": "assets/Maps/MPP_EK_DjinnSpouseRoom.tmx",
            "When": null
        },
        {
            "LogName": "Djinn - Map Addition - MPP_EK_SandyHouse",
            "Action": "Load",
            "Target": "Maps/MPP_EK_SandyHouse",
            "FromFile": "assets/Maps/MPP_EK_SandyHouse.tmx",
            "When": null
        },
        {
            "LogName": "Djinn - Map Addition - MPP_EK_SandyHouse_Improved",
            "Action": "Load",
            "Target": "Maps/MPP_EK_SandyHouse_Improved",
            "FromFile": "assets/Maps/MPP_EK_SandyHouse_Improved.tmx",
            "When": null
        },

        
        {
            "LogName": "Kraken - 25238/code/Maps/Additions - DeveloperNotes",
            "Action": "EditData",
            "Target": "Characters/Dialogue/MPP_EK_DeveloperNotes",
            "Entries": {
                "DeveloperNotes_Maps_Additions_Kraken.001": "+--------------------------------------------+",
                "DeveloperNotes_Maps_Additions_Kraken.002": "|                 Maps/Kraken                |",
                "DeveloperNotes_Maps_Additions_Kraken.003": "+--------------------------------------------+"
            }
        },
        {
            "LogName": "Kraken - Map Addition - MPP_EK_Beach",
            "Action": "Load",
            "Target": "Maps/MPP_EK_Beach",
            "FromFile": "assets/Maps/MPP_EK_Beach.tmx",
            "When": null
        },
        {
            "LogName": "Kraken - Map Addition - MPP_EK_KrakenRoom",
            "Action": "Load",
            "Target": "Maps/MPP_EK_KrakenRoom",
            "FromFile": "assets/Maps/MPP_EK_KrakenRoom.tmx",
            "When": null
        },
        {
            "LogName": "Kraken - Map Addition - MPP_EK_SamHouse",
            "Action": "Load",
            "Target": "Maps/MPP_EK_SamHouse",
            "FromFile": "assets/Maps/MPP_EK_SamHouse.tmx",
            "When": null
        },
        {
            "LogName": "Kraken - Map Addition - MPP_EK_KrakenSpouseArea",
            "Action": "Load",
            "Target": "Maps/MPP_EK_KrakenSpouseArea",
            "FromFile": "assets/Maps/MPP_EK_KrakenSpouseArea.tmx",
            "When": null
        },
        {
            "LogName": "Kraken - Map Addition - MPP_EK_KrakenSpouseRoom",
            "Action": "Load",
            "Target": "Maps/MPP_EK_KrakenSpouseRoom",
            "FromFile": "assets/Maps/MPP_EK_KrakenSpouseRoom.tmx",
            "When": null
        }
    ]
}